telespider/__init__.py
telespider/__main__.py
telespider/app.py
telespider/config.py
telespider/console.py
telespider/scrapper/__init__.py
telespider/scrapper/channel.py
telespider/scrapper/scrapper.py
telespider/scrapper/types.py
telespider-0.2.4.dist-info/LICENSE
telespider-0.2.4.dist-info/METADATA
telespider-0.2.4.dist-info/WHEEL
telespider-0.2.4.dist-info/entry_points.txt
telespider-0.2.4.dist-info/RECORD
