Metadata-Version: 2.1
Name: telespider
Version: 0.2.4
Summary: recursively parsing tg channels
License: MIT
Author: andrewsap
Author-email: andrewsapw@gmail.com
Requires-Python: >=3.10,<4.0
Classifier: License :: OSI Approved :: MIT License
Classifier: Programming Language :: Python :: 3
Classifier: Programming Language :: Python :: 3.10
Classifier: Programming Language :: Python :: 3.11
Requires-Dist: click (>=8.1.3,<9.0.0)
Requires-Dist: pydantic (>=1.10.7,<2.0.0)
Requires-Dist: pyrogram (>=2.0.103,<3.0.0)
Requires-Dist: rich (>=13.3.4,<14.0.0)
Requires-Dist: tgcrypto (>=1.2.5,<2.0.0)
Requires-Dist: uvloop (>=0.17.0,<0.18.0)
